modular_odm-0.3.0.dist-info/DESCRIPTION.rst
modular_odm-0.3.0.dist-info/METADATA
modular_odm-0.3.0.dist-info/metadata.json
modular_odm-0.3.0.dist-info/RECORD
modular_odm-0.3.0.dist-info/top_level.txt
modular_odm-0.3.0.dist-info/WHEEL
modularodm/__init__.py
modularodm/cache.py
modularodm/exceptions.py
modularodm/frozen.py
modularodm/signals.py
modularodm/storedobject.py
modularodm/utils.py
modularodm/writequeue.py
modularodm/ext/__init__.py
modularodm/ext/concurrency.py
modularodm/ext/odmflask.py
modularodm/fields/__init__.py
modularodm/fields/abstractforeignfield.py
modularodm/fields/booleanfield.py
modularodm/fields/datetimefield.py
modularodm/fields/dictionaryfield.py
modularodm/fields/field.py
modularodm/fields/floatfield.py
modularodm/fields/foreign.py
modularodm/fields/foreignfield.py
modularodm/fields/integerfield.py
modularodm/fields/listfield.py
modularodm/fields/lists.py
modularodm/fields/objectidfield.py
modularodm/fields/stringfield.py
modularodm/query/__init__.py
modularodm/query/query.py
modularodm/query/querydialect.py
modularodm/query/queryset.py
modularodm/storage/__init__.py
modularodm/storage/base.py
modularodm/storage/ephemeralstorage.py
modularodm/storage/mongostorage.py
modularodm/storage/picklestorage.py
modularodm/translators/__init__.py
modularodm/validators/__init__.py
