Metadata-Version: 2.0
Name: modular-odm
Version: 0.3.0
Summary: A Pythonic Object Data Manager
Home-page: https://github.com/CenterForOpenScience/modular-odm
Author: Center for Open Science
Author-email: contact@centerforopenscience.org
License: UNKNOWN
Keywords: odm,nosql,mongo,mongodb
Platform: UNKNOWN
Classifier: Development Status :: 3 - Alpha
Classifier: Intended Audience :: Developers
Classifier: Programming Language :: Python :: 2
Classifier: Programming Language :: Python :: 2.7
Requires-Dist: Flask
Requires-Dist: blinker
Requires-Dist: pymongo
Requires-Dist: python-dateutil
